odoo/addons/stock_picking_partner_brand/README.rst
odoo/addons/stock_picking_partner_brand/__init__.py
odoo/addons/stock_picking_partner_brand/__manifest__.py
odoo/addons/stock_picking_partner_brand/i18n/it.po
odoo/addons/stock_picking_partner_brand/i18n/stock_picking_partner_brand.pot
odoo/addons/stock_picking_partner_brand/models/__init__.py
odoo/addons/stock_picking_partner_brand/models/stock_picking.py
odoo/addons/stock_picking_partner_brand/readme/CONFIGURE.md
odoo/addons/stock_picking_partner_brand/readme/CONTEXT.md
odoo/addons/stock_picking_partner_brand/readme/CONTRIBUTORS.md
odoo/addons/stock_picking_partner_brand/readme/CREDITS.md
odoo/addons/stock_picking_partner_brand/readme/DESCRIPTION.md
odoo/addons/stock_picking_partner_brand/readme/HISTORY.md
odoo/addons/stock_picking_partner_brand/readme/INSTALL.md
odoo/addons/stock_picking_partner_brand/readme/ROADMAP.md
odoo/addons/stock_picking_partner_brand/readme/USAGE.md
odoo/addons/stock_picking_partner_brand/static/description/icon.png
odoo/addons/stock_picking_partner_brand/static/description/icon.svg
odoo/addons/stock_picking_partner_brand/static/description/index.html
odoo/addons/stock_picking_partner_brand/tests/__init__.py
odoo/addons/stock_picking_partner_brand/tests/test_stock_picking_partner_brand.py
odoo_addon_stock_picking_partner_brand-18.0.1.0.0.4.dist-info/METADATA
odoo_addon_stock_picking_partner_brand-18.0.1.0.0.4.dist-info/WHEEL
odoo_addon_stock_picking_partner_brand-18.0.1.0.0.4.dist-info/top_level.txt
odoo_addon_stock_picking_partner_brand-18.0.1.0.0.4.dist-info/RECORD
