Metadata-Version: 2.1
Name: odoo-addon-stock_picking_partner_brand
Version: 18.0.1.0.0.4
Requires-Python: >=3.10
Requires-Dist: odoo-addon-partner_brand==18.0.*
Requires-Dist: odoo-addon-stock_brand==18.0.*
Requires-Dist: odoo==18.0.*
Summary: Automatically sets the brand on a Stock Picking based on the selected partner's brand.
Home-page: https://github.com/OCA/brand
License: AGPL-3
Author: O.B.S. Solutions, Odoo Community Association (OCA)
Author-email: support@odoo-community.org
Classifier: Programming Language :: Python
Classifier: Framework :: Odoo
Classifier: Framework :: Odoo :: 18.0
Classifier: License :: OSI Approved :: GNU Affero General Public License v3
Classifier: Development Status :: 3 - Alpha
